CHANGES.txt
CONTRIBUTORS.txt
MANIFEST.in
README.txt
setup.cfg
setup.py
collective/__init__.py
collective.doormat.egg-info/PKG-INFO
collective.doormat.egg-info/SOURCES.txt
collective.doormat.egg-info/dependency_links.txt
collective.doormat.egg-info/entry_points.txt
collective.doormat.egg-info/namespace_packages.txt
collective.doormat.egg-info/not-zip-safe
collective.doormat.egg-info/paster_plugins.txt
collective.doormat.egg-info/requires.txt
collective.doormat.egg-info/top_level.txt
collective/doormat/README.txt
collective/doormat/__init__.py
collective/doormat/config.py
collective/doormat/configure.zcml
collective/doormat/interfaces.py
collective/doormat/vocabularies.py
collective/doormat/browser/__init__.py
collective/doormat/browser/__init__.pyo
collective/doormat/browser/configure.zcml
collective/doormat/browser/doormat_viewlet.pt
collective/doormat/browser/settings.py
collective/doormat/browser/viewlets.py
collective/doormat/profiles/default/browserlayer.xml
collective/doormat/profiles/default/controlpanel.xml
collective/doormat/profiles/default/cssregistry.xml
collective/doormat/profiles/default/metadata.xml
collective/doormat/profiles/default/registry.xml
collective/doormat/profiles/default/skins.xml
collective/doormat/profiles/default/viewlets.xml
collective/doormat/skins/collective_doormat/cdoormat.css
collective/doormat/tests/__init__.py
collective/doormat/tests/__init__.pyo
collective/doormat/tests/base.py
collective/doormat/tests/test_doctest.py
docs/HISTORY.txt
docs/INSTALL.txt
docs/LICENSE.GPL
docs/LICENSE.txt