Metadata-Version: 1.0
Name: collective.doormat
Version: 0.1
Summary: Adds a doormat viewlet and installs it in the Plone
Home-page: http://plone.org/products/collective.doormat
Author: Christian Ledermann
Author-email: christian.ledermann@gmail.com
License: GPL
Platform: UNKNOWN
Classifier: Framework :: Plone
Classifier: Framework :: Plone :: 4.0
Classifier: Framework :: Plone :: 4.1
Classifier: License :: OSI Approved :: GNU General Public License (GPL)
